[
    {
        "tags":["심플","무채색"],
        "title":"심플 이즈 더 베스트 🖤",
        "comment":"#무난한게_최고야 #기본템_환영"
    },
    {
        "tags":["파스텔","집"],
        "title": "여기 선물에 갬성 묻었어요 🦋",
        "comment": "#선물도_감성적으로 #선물_인증샷_필수"
    },
    {
        "tags":["실용성","건강"],
        "title": "선물계 실용주의자 🤔",
        "comment": "#이쁜_쓰레기_사절 #꽃보다_기프티콘"
    },
    {
        "tags": ["유니크","디자인"],
        "title": "나만을 위해 특별한 걸로 😝",
        "comment": "#유니크한_디자인 #신기한거_대환영"
    },
    {
        "tags": ["캐주얼","디자인"],
        "title": "이쁜 건 사야해, 아니 받을래! 🌸",
        "comment": "#이건_사야해 #이쁜_쓰레기라도_좋아"
    },
    {
        "tags": ["실용성","야외"],
        "title": "좋아! 내일 당장 써봐야지 😎",
        "comment": "#실용적인걸로_부탁해 #바로_자랑할거야"
    },
    {
        "tags": ["디자인","야외"],
        "title": "취향 저격? 그거 쉬울 수도 🎯",
        "comment": "#이쁜게_최고야 #이거_어디꺼야?"
    },
    {
        "tags": ["달달","간식"],
        "title": "혹시 설탕 요정?🧚",
        "comment": "#달달"
    }
]

